{"chunk_definitions":[{"row":139,"row_count":1,"visible":true,"expansion_state":0,"options":{"engine":"r","label":"unnamed-chunk-111"},"document_id":"CC0FBC75","chunk_id":"c1qy7mdysidia","chunk_label":"unnamed-chunk-1"},{"row":159,"row_count":1,"visible":true,"expansion_state":0,"options":{"engine":"r","echo":false,"label":"unnamed-chunk-2"},"document_id":"CC0FBC75","chunk_id":"clh4fvsu1hgpy","chunk_label":"unnamed-chunk-2"},{"row":172,"row_count":1,"visible":true,"expansion_state":0,"options":{"engine":"r","tidy":true,"tidy.opts":{"width.cutoff":72},"label":"unnamed-chunk-3"},"document_id":"CC0FBC75","chunk_id":"cwv452m7fejrg","chunk_label":"unnamed-chunk-3"},{"row":182,"row_count":1,"visible":true,"expansion_state":0,"options":{"engine":"r","tidy":true,"tidy.opts":{"width.cutoff":72},"label":"unnamed-chunk-4"},"document_id":"CC0FBC75","chunk_id":"crufo28iuerwb","chunk_label":"unnamed-chunk-4"},{"row":2937,"row_count":1,"visible":true,"expansion_state":0,"options":{"engine":"r","tidy":true,"tidy.opts":{"width.cutoff":72},"eval":false,"label":"unnamed-chunk-127"},"document_id":"CC0FBC75","chunk_id":"cap8d2038o94q","chunk_label":"unnamed-chunk-44"}],"doc_write_time":1668182822,"chunk_rendered_width":700}